zdppy_elasticsearch/__init__.py
zdppy_elasticsearch/elasticsearch.py
zdppy_elasticsearch-1.0.1.dist-info/METADATA
zdppy_elasticsearch-1.0.1.dist-info/LICENSE
zdppy_elasticsearch-1.0.1.dist-info/WHEEL
zdppy_elasticsearch-1.0.1.dist-info/RECORD
