Metadata-Version: 2.1
Name: zdppy-elasticsearch
Version: 1.0.1
Summary: python操作ElasticSearch的基础组件
Home-page: https://github.com/zhangdapeng520/zdppy_elasticsearch
License: MIT
Keywords: zdppy,ElasticSearch,search,zhangdapeng
Author: 张大鹏
Author-email: 1156956636@qq.com
Requires-Python: >=3.9,<4.0
Classifier: License :: OSI Approved :: MIT License
Classifier: Programming Language :: Python :: 3
Classifier: Programming Language :: Python :: 3.9
Classifier: Programming Language :: Python :: 3.10
Classifier: Programming Language :: Python :: 3.11
Requires-Dist: zdppy-requests (>=0.1.3,<0.2.0)
Project-URL: Documentation, https://github.com/zhangdapeng520/zdppy_elasticsearch
Project-URL: Repository, https://github.com/zhangdapeng520/zdppy_elasticsearch
